yusholib/__init__.py
yusholib/events.py
yusholib/ipscan.py
yusholib/logger.py
yusholib-0.0.3.dist-info/LICENSE
yusholib-0.0.3.dist-info/METADATA
yusholib-0.0.3.dist-info/WHEEL
yusholib-0.0.3.dist-info/top_level.txt
yusholib-0.0.3.dist-info/RECORD
