Metadata-Version: 2.1
Name: yusholib
Version: 0.0.3
Summary: A small utility package
Home-page: https://github.com/yushodev/yusholib
Author: yusho
Author-email: yushodev <pxlized2@gmail.com>
License: MIT
Project-URL: Homepage, https://github.com/yushodev/yusholib
Project-URL: Bug Tracker, https://github.com/yushodev/yusholib/issues
Classifier: Programming Language :: Python :: 3
Classifier: License :: OSI Approved :: MIT License
Classifier: Operating System :: OS Independent
Requires-Python: >=3.7
License-File: LICENSE
